flonb/__init__.py
flonb/task.py
tests/__init__.py
tests/test_basic_deps.py
tests/test_caching.py
tests/test_container_deps.py
tests/test_dynamic_deps.py
tests/test_errors.py
tests/test_partial.py
tests/test_task_func.py
flonb-0.1.4.dist-info/LICENSE
flonb-0.1.4.dist-info/METADATA
flonb-0.1.4.dist-info/WHEEL
flonb-0.1.4.dist-info/top_level.txt
flonb-0.1.4.dist-info/RECORD
