Metadata-Version: 2.1
Name: flonb
Version: 0.1.4
Summary: Rapid-iteration data pipelines with automagic caching + parameter passing.
Home-page: https://github.com/hazbottles/flonb
Author: hazbottles
Classifier: Programming Language :: Python :: 3
Classifier: License :: OSI Approved :: MIT License
Classifier: Operating System :: OS Independent
Requires-Python: >=3.6
License-File: LICENSE
Requires-Dist: dask
